Metadata-Version: 1.1
Name: telegram-printer
Version: 0.0.1
Summary: Send the telegram message & print at the same time
Home-page: UNKNOWN
Author: TheBlackHero55
Author-email: theblackhero2@gmail.com
License: MIT
Keywords: telegram,print,tg,printer,prints,bold,underline
Platform: UNKNOWN
Classifier: Development Status :: 5 - Production/Stable
Classifier: Intended Audience :: Education
Classifier: Operating System :: Microsoft :: Windows :: Windows 10
Classifier: License :: OSI Approved :: MIT License
Classifier: Programming Language :: Python :: 3
